CHANGES.txt
LICENSE.txt
README.txt
setup.py
js/__init__.py
js.bootstrap_timepicker.egg-info/PKG-INFO
js.bootstrap_timepicker.egg-info/SOURCES.txt
js.bootstrap_timepicker.egg-info/dependency_links.txt
js.bootstrap_timepicker.egg-info/entry_points.txt
js.bootstrap_timepicker.egg-info/namespace_packages.txt
js.bootstrap_timepicker.egg-info/not-zip-safe
js.bootstrap_timepicker.egg-info/requires.txt
js.bootstrap_timepicker.egg-info/top_level.txt
js/bootstrap_timepicker/__init__.py
js/bootstrap_timepicker/test_bootstrap_timepicker.txt
js/bootstrap_timepicker/resources/README.txt
js/bootstrap_timepicker/resources/bootstrap-timepicker.css
js/bootstrap_timepicker/resources/bootstrap-timepicker.js
js/bootstrap_timepicker/resources/bootstrap-timepicker.min.css
js/bootstrap_timepicker/resources/bootstrap-timepicker.min.js