Metadata-Version: 1.0
Name: js.bootstrap-timepicker
Version: 0.2.1
Summary: Fanstatic packaging of Bootstrap Timepicker
Home-page: https://github.com/disko/js.bootstrap_timepicker
Author: Andreas Kaiser
Author-email: disko@binary-punks.com
License: BSD
Platform: UNKNOWN
